epione/.DS_Store
epione/__init__.py
epione/bulk/__init__.py
epione/bulk/_bigwig.py
epione/bulk/_getScorePerBigWigBin.py
epione/bulk/_mapreduce.py
epione/bulk/_utilities.py
epione-0.0.1rc1.dist-info/licenses/LICENSE
epione-0.0.1rc1.dist-info/WHEEL
epione-0.0.1rc1.dist-info/METADATA
epione-0.0.1rc1.dist-info/RECORD
