Metadata-Version: 2.4
Name: epione
Version: 0.0.1rc1
Summary: EpiOne: Generative cartography of single-cell epigenomes
Keywords: bioinformatics,deep-learning,single-cell,ATAC-seq
Author-email: Zehua Zeng <starlitnightly@gmail.com>
Requires-Python: >=3.9
Classifier: Intended Audience :: Science/Research
Classifier: Natural Language :: English
Classifier: Operating System :: MacOS :: MacOS X
Classifier: Operating System :: POSIX :: Linux
Classifier: Programming Language :: Python :: 3
Classifier: Programming Language :: Python :: 3.8
Classifier: Programming Language :: Python :: 3.9
Classifier: Topic :: Scientific/Engineering :: Bio-Informatics
License-File: LICENSE
Requires-Dist: muon>=0.1
Requires-Dist: pyBigWig>=0.3
Requires-Dist: loompy>=3.0.7
Requires-Dist: pyrange
Requires-Dist: MOODS-python ; extra == "full"
Requires-Dist: pysam ; extra == "full"
Requires-Dist: pynndescent ; extra == "full"
Requires-Dist: pyjaspar ; extra == "full"
Requires-Dist: omicverse ; extra == "full"
Project-URL: Github, https://github.com/aristoteleo/epione
Provides-Extra: full
